mistralgptintegration/__init__.py
mistralgptintegration/integration.py
mistralgptintegration-2025.5.180912.dist-info/licenses/LICENSE
tests/__init__.py
tests/test_integration.py
mistralgptintegration-2025.5.180912.dist-info/METADATA
mistralgptintegration-2025.5.180912.dist-info/WHEEL
mistralgptintegration-2025.5.180912.dist-info/top_level.txt
mistralgptintegration-2025.5.180912.dist-info/RECORD
