Metadata-Version: 2.4
Name: MistralGPTIntegration
Version: 2025.5.180912
Summary: Integration utility for Mistral AI API to provide GPT-based functionalities.
Home-page: https://github.com/chigwell/MistralGPTIntegration
Author: Eugene Evstafev
Author-email: chigwel@gmail.com
Classifier: License :: OSI Approved :: MIT License
Classifier: Development Status :: 3 - Alpha
Classifier: Intended Audience :: Developers
Classifier: Programming Language :: Python :: 3
Classifier: Operating System :: OS Independent
Requires-Python: >=3.6
License-File: LICENSE
Requires-Dist: mistralai
Dynamic: author
Dynamic: author-email
Dynamic: classifier
Dynamic: description
Dynamic: description-content-type
Dynamic: home-page
Dynamic: license-file
Dynamic: requires-dist
Dynamic: requires-python
Dynamic: summary
